pipTutorial/__init__.py
pipTutorial/__main__.py
pipTutorial/funcs.py
pipTutorial-1.0.dist-info/LICENSE
pipTutorial-1.0.dist-info/METADATA
pipTutorial-1.0.dist-info/WHEEL
pipTutorial-1.0.dist-info/top_level.txt
pipTutorial-1.0.dist-info/RECORD
