Metadata-Version: 2.1
Name: pipTutorial
Version: 1.0
Summary: A useful module
Author: Man Foo
Author-email: foomail@foo.example
License-File: LICENSE
Requires-Dist: pandas
Requires-Dist: numpy
Requires-Dist: matplotlib
